[
    {
        "type": "message",
        "subtype": "file_share",
        "text": "<@U8RFVCE7P> uploaded a file: <https:\/\/info6205-03-37196.slack.com\/files\/U8RFVCE7P\/FA45N16DV\/teams.csv|Teams> and commented: This is what I have so far. Please slack me if you need to add a team or correct anything",
        "file": {
            "id": "FA45N16DV",
            "created": 1523193148,
            "timestamp": 1523193148,
            "name": "Teams.csv",
            "title": "Teams",
            "mimetype": "text\/csv",
            "filetype": "csv",
            "pretty_type": "CSV",
            "user": "U8RFVCE7P",
            "editable": true,
            "size": 622,
            "mode": "snippet",
            "is_external": false,
            "external_type": "",
            "is_public": true,
            "public_url_shared": false,
            "display_as_bot": false,
            "username": "",
            "url_private": "https:\/\/files.slack.com\/files-pri\/T8RCESJMQ-FA45N16DV\/teams.csv?t=xoxe-297422902738-350782568738-350919557621-846260e7fdf25d28d6da98102605ccae",
            "url_private_download": "https:\/\/files.slack.com\/files-pri\/T8RCESJMQ-FA45N16DV\/download\/teams.csv?t=xoxe-297422902738-350782568738-350919557621-846260e7fdf25d28d6da98102605ccae",
            "permalink": "https:\/\/info6205-03-37196.slack.com\/files\/U8RFVCE7P\/FA45N16DV\/teams.csv",
            "permalink_public": "https:\/\/slack-files.com\/T8RCESJMQ-FA45N16DV-fb7ce928c1",
            "edit_link": "https:\/\/info6205-03-37196.slack.com\/files\/U8RFVCE7P\/FA45N16DV\/teams.csv\/edit",
            "preview": "301\tNithin Kartha\tVignesh Karthikeyan\t\r\n302\tJin Lin\t Zhimei Liang\t\r\n303\tAnkit Yadav\t\t\r\n304\tShouting Lyu\tChang Liu \t\r\n305\tBoyu Chen\t\t\r",
            "preview_highlight": "<div class=\"CodeMirror cm-s-default CodeMirrorServer\" oncopy=\"if(event.clipboardData){event.clipboardData.setData('text\/plain',window.getSelection().toString().replace(\/\\u200b\/g,''));event.preventDefault();event.stopPropagation();}\">\n<div class=\"CodeMirror-code\">\n<div><pre>301 Nithin Kartha   Vignesh Karthikeyan <\/pre><\/div>\n<div><pre>302 Jin Lin  Zhimei Liang   <\/pre><\/div>\n<div><pre>303 Ankit Yadav     <\/pre><\/div>\n<div><pre>304 Shouting Lyu    Chang Liu   <\/pre><\/div>\n<div><pre>305 Boyu Chen       <\/pre><\/div>\n<div><pre><\/pre><\/div>\n<\/div>\n<\/div>\n",
            "lines": 20,
            "lines_more": 15,
            "preview_is_truncated": false,
            "channels": [],
            "groups": [],
            "ims": [],
            "comments_count": 1,
            "initial_comment": {
                "id": "FcA2SSLE5S",
                "created": 1523193148,
                "timestamp": 1523193148,
                "user": "U8RFVCE7P",
                "is_intro": true,
                "comment": "This is what I have so far. Please slack me if you need to add a team or correct anything"
            }
        },
        "user": "U8RFVCE7P",
        "upload": true,
        "display_as_bot": false,
        "username": "scalaprof",
        "bot_id": null,
        "ts": "1523193149.000017"
    },
    {
        "type": "message",
        "subtype": "file_share",
        "text": "<@U8RFVCE7P> uploaded a file: <https:\/\/info6205-03-37196.slack.com\/files\/U8RFVCE7P\/FA2KRUH3K\/updated_teams.csv|Updated Teams> and commented: Only a few hours before team makeup deadline",
        "file": {
            "id": "FA2KRUH3K",
            "created": 1523223072,
            "timestamp": 1523223072,
            "name": "Updated_Teams.csv",
            "title": "Updated Teams",
            "mimetype": "text\/csv",
            "filetype": "csv",
            "pretty_type": "CSV",
            "user": "U8RFVCE7P",
            "editable": true,
            "size": 783,
            "mode": "snippet",
            "is_external": false,
            "external_type": "",
            "is_public": true,
            "public_url_shared": false,
            "display_as_bot": false,
            "username": "",
            "url_private": "https:\/\/files.slack.com\/files-pri\/T8RCESJMQ-FA2KRUH3K\/updated_teams.csv?t=xoxe-297422902738-350782568738-350919557621-846260e7fdf25d28d6da98102605ccae",
            "url_private_download": "https:\/\/files.slack.com\/files-pri\/T8RCESJMQ-FA2KRUH3K\/download\/updated_teams.csv?t=xoxe-297422902738-350782568738-350919557621-846260e7fdf25d28d6da98102605ccae",
            "permalink": "https:\/\/info6205-03-37196.slack.com\/files\/U8RFVCE7P\/FA2KRUH3K\/updated_teams.csv",
            "permalink_public": "https:\/\/slack-files.com\/T8RCESJMQ-FA2KRUH3K-87633244e4",
            "edit_link": "https:\/\/info6205-03-37196.slack.com\/files\/U8RFVCE7P\/FA2KRUH3K\/updated_teams.csv\/edit",
            "preview": "Team Number\tFirst Name\tSecond Name\tThird Name\r\n301\tNithin Kartha\tVignesh Karthikeyan\t\r\n302\tJin Lin\t Zhimei Liang\t\r\n303\tAnkit Yadav\t\t\r\n304\tShouting Lyu\tChang Liu \t\r",
            "preview_highlight": "<div class=\"CodeMirror cm-s-default CodeMirrorServer\" oncopy=\"if(event.clipboardData){event.clipboardData.setData('text\/plain',window.getSelection().toString().replace(\/\\u200b\/g,''));event.preventDefault();event.stopPropagation();}\">\n<div class=\"CodeMirror-code\">\n<div><pre>Team Number First Name  Second Name Third Name<\/pre><\/div>\n<div><pre>301 Nithin Kartha   Vignesh Karthikeyan <\/pre><\/div>\n<div><pre>302 Jin Lin  Zhimei Liang   <\/pre><\/div>\n<div><pre>303 Ankit Yadav     <\/pre><\/div>\n<div><pre>304 Shouting Lyu    Chang Liu   <\/pre><\/div>\n<div><pre><\/pre><\/div>\n<\/div>\n<\/div>\n",
            "lines": 23,
            "lines_more": 18,
            "preview_is_truncated": false,
            "channels": [],
            "groups": [],
            "ims": [],
            "comments_count": 1,
            "initial_comment": {
                "id": "FcA33EPCEP",
                "created": 1523223072,
                "timestamp": 1523223072,
                "user": "U8RFVCE7P",
                "is_intro": true,
                "comment": "Only a few hours before team makeup deadline"
            }
        },
        "user": "U8RFVCE7P",
        "upload": true,
        "display_as_bot": false,
        "username": "scalaprof",
        "bot_id": null,
        "ts": "1523223073.000013"
    },
    {
        "type": "message",
        "subtype": "file_share",
        "text": "<@U8RFVCE7P> uploaded a file: <https:\/\/info6205-03-37196.slack.com\/files\/U8RFVCE7P\/FA37TMTH8\/latest_teams.csv|latest teams>",
        "file": {
            "id": "FA37TMTH8",
            "created": 1523239481,
            "timestamp": 1523239481,
            "name": "latest_teams.csv",
            "title": "latest teams",
            "mimetype": "text\/csv",
            "filetype": "csv",
            "pretty_type": "CSV",
            "user": "U8RFVCE7P",
            "editable": true,
            "size": 905,
            "mode": "snippet",
            "is_external": false,
            "external_type": "",
            "is_public": true,
            "public_url_shared": false,
            "display_as_bot": false,
            "username": "",
            "url_private": "https:\/\/files.slack.com\/files-pri\/T8RCESJMQ-FA37TMTH8\/latest_teams.csv?t=xoxe-297422902738-350782568738-350919557621-846260e7fdf25d28d6da98102605ccae",
            "url_private_download": "https:\/\/files.slack.com\/files-pri\/T8RCESJMQ-FA37TMTH8\/download\/latest_teams.csv?t=xoxe-297422902738-350782568738-350919557621-846260e7fdf25d28d6da98102605ccae",
            "permalink": "https:\/\/info6205-03-37196.slack.com\/files\/U8RFVCE7P\/FA37TMTH8\/latest_teams.csv",
            "permalink_public": "https:\/\/slack-files.com\/T8RCESJMQ-FA37TMTH8-99cf955bae",
            "edit_link": "https:\/\/info6205-03-37196.slack.com\/files\/U8RFVCE7P\/FA37TMTH8\/latest_teams.csv\/edit",
            "preview": "Team Number\tFirst Name\tSecond Name\tThird Name\r\n301\tNithin Kartha\tVignesh Karthikeyan\t\r\n302\tJin Lin\tZhimei Liang\t\r\n303\tAnkit Yadav\t\t\r\n304\tShouting Lyu\tChang Liu \t\r",
            "preview_highlight": "<div class=\"CodeMirror cm-s-default CodeMirrorServer\" oncopy=\"if(event.clipboardData){event.clipboardData.setData('text\/plain',window.getSelection().toString().replace(\/\\u200b\/g,''));event.preventDefault();event.stopPropagation();}\">\n<div class=\"CodeMirror-code\">\n<div><pre>Team Number First Name  Second Name Third Name<\/pre><\/div>\n<div><pre>301 Nithin Kartha   Vignesh Karthikeyan <\/pre><\/div>\n<div><pre>302 Jin Lin Zhimei Liang    <\/pre><\/div>\n<div><pre>303 Ankit Yadav     <\/pre><\/div>\n<div><pre>304 Shouting Lyu    Chang Liu   <\/pre><\/div>\n<div><pre><\/pre><\/div>\n<\/div>\n<\/div>\n",
            "lines": 27,
            "lines_more": 22,
            "preview_is_truncated": false,
            "channels": [],
            "groups": [],
            "ims": [],
            "comments_count": 0
        },
        "user": "U8RFVCE7P",
        "upload": true,
        "display_as_bot": false,
        "username": "scalaprof",
        "bot_id": null,
        "ts": "1523239481.000157"
    }
]